{
  "environment": "web",
  "format": "html",
  "prefix": "../../elements",
  "mainga": "UA-49880327-14",
  "updated": "2020-10-06T14:23:41+11:00",
  "id": "automate-feedback-1",
  "duration": 54,
  "title": "Automate Feedback - Session 1",
  "authors": "Brandon Neo",
  "summary": "Automate Feedback Session 1",
  "source": "ANZ-automate-feedback-1.md",
  "theme": "",
  "status": [
    "published"
  ],
  "category": [
    "automate-feedback"
  ],
  "tags": [
    "anz"
  ],
  "feedback": "mailto:d1-apac@dynatrace.com",
  "ga": "UA-175467274-1",
  "url": "automate-feedback-1"
}
